CHANGES.txt
LICENSE
README.txt
setup.py
src/svnhelper/README.txt
src/svnhelper/__init__.py
src/svnhelper/command.py
src/svnhelper/command.txt
src/svnhelper/core.py
src/svnhelper/default.cfg
src/svnhelper/recipe.py
src/svnhelper/script.py
src/svnhelper/testing.py
src/svnhelper/testing.txt
src/svnhelper/tests.py
src/svnhelper/utils.py
src/svnhelper/virtualenv
src/svnhelper.egg-info/PKG-INFO
src/svnhelper.egg-info/SOURCES.txt
src/svnhelper.egg-info/dependency_links.txt
src/svnhelper.egg-info/entry_points.txt
src/svnhelper.egg-info/namespace_packages.txt
src/svnhelper.egg-info/not-zip-safe
src/svnhelper.egg-info/requires.txt
src/svnhelper.egg-info/top_level.txt
src/svnhelper/tests/my.testing/LICENSE
src/svnhelper/tests/my.testing/setup.py
src/svnhelper/tests/my.testing/my/__init__.py
src/svnhelper/tests/my.testing/my/testing/README.txt
src/svnhelper/tests/my.testing/my/testing/__init__.py
