Metadata-Version: 1.0
Name: svnhelper
Version: 0.2
Summary: some svn utils to easily import/checkout packages
Home-page: UNKNOWN
Author: Gael Pasgrimaud
Author-email: gael@gawel.org
License: GPL
Platform: UNKNOWN
Classifier: Programming Language :: Python
Classifier: Topic :: Software Development :: Libraries :: Python Modules
